opsys_tec_controller/__init__.py
opsys_tec_controller/device_types.py
opsys_tec_controller/ldt_5910c_controller.py
opsys_tec_controller/tec_abstract.py
opsys_tec_controller/tec_controller.py
opsys_tec_controller-0.0.4.dist-info/LICENSE
opsys_tec_controller-0.0.4.dist-info/METADATA
opsys_tec_controller-0.0.4.dist-info/WHEEL
opsys_tec_controller-0.0.4.dist-info/top_level.txt
opsys_tec_controller-0.0.4.dist-info/RECORD
